packageRitz/__init__.py
packageRitz-0.0.1.dist-info/LICENSE.txt
packageRitz-0.0.1.dist-info/METADATA
packageRitz-0.0.1.dist-info/WHEEL
packageRitz-0.0.1.dist-info/top_level.txt
packageRitz-0.0.1.dist-info/RECORD
