Metadata-Version: 2.1
Name: packageRitz
Version: 0.0.1
Summary: Say hello
Home-page: UNKNOWN
Author: Ritz
Author-email: UNKNOWN
License: UNKNOWN
Platform: UNKNOWN
